odoo10_addon_stock_helper-10.0.1.1.1-py3.8-nspkg.pth
odoo/addons/stock_helper/README.rst
odoo/addons/stock_helper/__init__.py
odoo/addons/stock_helper/__manifest__.py
odoo/addons/stock_helper/i18n/stock_helper.pot
odoo/addons/stock_helper/models/__init__.py
odoo/addons/stock_helper/models/stock_location.py
odoo/addons/stock_helper/readme/CONTRIBUTORS.rst
odoo/addons/stock_helper/readme/DESCRIPTION.rst
odoo/addons/stock_helper/static/description/icon.png
odoo/addons/stock_helper/static/description/index.html
odoo/addons/stock_helper/tests/__init__.py
odoo/addons/stock_helper/tests/common.py
odoo/addons/stock_helper/tests/test_location_is_sublocation_of.py
odoo10_addon_stock_helper-10.0.1.1.1.dist-info/METADATA
odoo10_addon_stock_helper-10.0.1.1.1.dist-info/WHEEL
odoo10_addon_stock_helper-10.0.1.1.1.dist-info/namespace_packages.txt
odoo10_addon_stock_helper-10.0.1.1.1.dist-info/top_level.txt
odoo10_addon_stock_helper-10.0.1.1.1.dist-info/RECORD
